README.md
setup.py
SQLAlchemyBlender.egg-info/PKG-INFO
SQLAlchemyBlender.egg-info/SOURCES.txt
SQLAlchemyBlender.egg-info/dependency_links.txt
SQLAlchemyBlender.egg-info/not-zip-safe
SQLAlchemyBlender.egg-info/requires.txt
SQLAlchemyBlender.egg-info/top_level.txt
example/__init__.py
example/app.py
sqlalchemy_blender/__init__.py
sqlalchemy_blender/dao.py
sqlalchemy_blender/database.py
sqlalchemy_blender/helpers.py
sqlalchemy_blender/processor.py
sqlalchemy_blender/types.py
sqlalchemy_blender/mixins/__init__.py
sqlalchemy_blender/mixins/abstracts.py
sqlalchemy_blender/mixins/columns.py
sqlalchemy_blender/mixins/core.py
sqlalchemy_blender/query/__init__.py
sqlalchemy_blender/query/buffer.py
sqlalchemy_blender/query/processor.py
test/__init__.py
test/test_querystring.py